filelean/__init__.py
filelean/constants.py
filelean/proof.py
filelean/utils.py
filelean/cli/__init__.py
filelean/cli/install.py
filelean/cli/log_config.py
filelean/cli/main.py
filelean/cli/utils.py
filelean-0.1.1.dist-info/LICENSE
filelean-0.1.1.dist-info/METADATA
filelean-0.1.1.dist-info/WHEEL
filelean-0.1.1.dist-info/entry_points.txt
filelean-0.1.1.dist-info/top_level.txt
filelean-0.1.1.dist-info/RECORD
