Metadata-Version: 2.1
Name: filelean
Version: 0.1.1
Summary: Interact with Lean4 through file-based communication.
Home-page: https://github.com/Lean-zh/FileLean
Author: Rex Wang
Author-email: 1073853456@qq.com
License: MIT license
Keywords: filelean
Platform: UNKNOWN
Classifier: Development Status :: 2 - Pre-Alpha
Classifier: Intended Audience :: Developers
Classifier: License :: OSI Approved :: MIT License
Classifier: Natural Language :: English
Classifier: Programming Language :: Python :: 3
Classifier: Programming Language :: Python :: 3.9
Requires-Python: >=3.6
Requires-Dist: click
Requires-Dist: loguru
Requires-Dist: pygithub
Requires-Dist: gitpython
Requires-Dist: pexpect
Requires-Dist: toml
